japan_basic_section/__init__.py
japan_basic_section/base_section.py
japan_basic_section/grid.py
japan_basic_section/origin_coords.py
japan_basic_section-0.0.3.dist-info/LICENSE
japan_basic_section-0.0.3.dist-info/METADATA
japan_basic_section-0.0.3.dist-info/WHEEL
japan_basic_section-0.0.3.dist-info/RECORD
