Metadata-Version: 2.1
Name: japan-basic-section
Version: 0.0.3
Summary: 国土基本図図郭を作成するためのパッケージです。
Author: nokonoko1203
Author-email: noreply@example.com
Requires-Python: >=3.9,<4.0
Classifier: Programming Language :: Python :: 3
Classifier: Programming Language :: Python :: 3.9
Classifier: Programming Language :: Python :: 3.10
Classifier: Programming Language :: Python :: 3.11
Requires-Dist: geopandas (>=0.12.2,<0.13.0)
